smartmodels/__init__.py
smartmodels/definitions.py
smartmodels/smartmodels.py
smartmodels/auths/__init__.py
smartmodels/cli/__init__.py
smartmodels/cli/config.py
smartmodels/cli/inventory.py
smartmodels/cli/main.py
smartmodels/cli/publish.py
smartmodels/cli/script.py
smartmodels/cli/setup.py
smartmodels/cli/surreal.py
smartmodels/cli/sync.py
smartmodels/cli/task.py
smartmodels/cli/wingdbstub.py
smartmodels/cli/workspace.py
smartmodels/helpers/__init__.py
smartmodels/helpers/faker.py
smartmodels/helpers/general.py
smartmodels/helpers/loaders.py
smartmodels/helpers/models.py
smartmodels/helpers/surreal.py
smartmodels/logic/__init__.py
smartmodels/logic/crawler.py
smartmodels/logic/inventory.py
smartmodels/logic/smartmodels.py
smartmodels/mapper/__init__.py
smartmodels/mapper/inventory.py
smartmodels/mapper/pollutants.py
smartmodels/mapper/weather/__init__.py
smartmodels/mapper/weather/aemet.py
smartmodels/mapper/weather/air_quality_index.py
smartmodels/mapper/weather/meteo.py
smartmodels/model/__init__.py
smartmodels/model/base.py
smartmodels/model/config.py
smartmodels/model/enums.py
smartmodels/model/fiware.py
smartmodels/model/inventory.py
smartmodels/model/script.py
smartmodels/model/smartmodels.py
smartmodels/model/task.py
smartmodels/model/generic/__init__.py
smartmodels/model/generic/maxmin.py
smartmodels/model/water/__init__.py
smartmodels/model/water/stream/__init__.py
smartmodels/model/weather/__init__.py
smartmodels/model/weather/air_quality_index.py
smartmodels/model/weather/meteo.py
smartmodels/model/weather/pollutants.py
smartmodels/ports/__init__.py
smartmodels/ports/preferences.py
smartmodels/sources/__init__.py
smartmodels/storage/__init__.py
smartmodels/storage/surreal.py
smartmodels/tokens/__init__.py
smartmodels-0.1.357.dist-info/AUTHORS.rst
smartmodels-0.1.357.dist-info/LICENSE
smartmodels-0.1.357.dist-info/METADATA
smartmodels-0.1.357.dist-info/WHEEL
smartmodels-0.1.357.dist-info/entry_points.txt
smartmodels-0.1.357.dist-info/top_level.txt
smartmodels-0.1.357.dist-info/RECORD
